folderpreview/__init__.py
folderpreview/folder_preview.py
folderpreview/installer.py
folderpreview/logger.py
folderpreview/config/__init__.py
folderpreview/config/config.py
folderpreview/config/resource.py
folderpreview/dbus/__init__.py
folderpreview/dbus/message_bus.py
folderpreview/dbus/thumbnailer.py
folderpreview/media/__init__.py
folderpreview/media/icon.py
folderpreview/media/media.py
folderpreview/media/media_decorator.py
folderpreview/media/thumb.py
folderpreview/renderer/__init__.py
folderpreview/renderer/thumb_renderer.py
folderpreview/renderer/tile_thumb_renderer.py
folderpreview/resources/template.thumbnailer
folderpreview-0.4.3.dist-info/LICENSE
folderpreview-0.4.3.dist-info/METADATA
folderpreview-0.4.3.dist-info/WHEEL
folderpreview-0.4.3.dist-info/entry_points.txt
folderpreview-0.4.3.dist-info/top_level.txt
folderpreview-0.4.3.dist-info/RECORD
