Metadata-Version: 2.1
Name: folderpreview
Version: 0.4.3
Summary: Generates folder preview thumb
Home-page: https://gitlab.com/hxss-linux/folderpreview
Author: hxss
Author-email: hxss@ya.ru
License: MIT
Keywords: folder,thumb
Platform: UNKNOWN
Classifier: Programming Language :: Python :: 3.6
Classifier: Programming Language :: Python :: 3.7
Classifier: Programming Language :: Python :: 3.8
Classifier: License :: OSI Approved :: MIT License
Classifier: Operating System :: POSIX :: Linux
Classifier: Topic :: Desktop Environment :: File Managers
Requires-Python: >=3.6.12
Requires-Dist: dbus-next (>=0.1.1)
Requires-Dist: pyxdg (>=0.26)
Requires-Dist: pyyaml (>=5.1)
Requires-Dist: parse (>=1.9.0)
Requires-Dist: pygobject (>=3.30.4)
Requires-Dist: pyvips (>=2.1.5)
